{
    "dishes": [
      {
        "id": "1a2b3c4d5e6f",
        "dishName": "宫保鸡丁",
        "restaurant": "百景园食堂",
        "imageData": "/imgs/gongbao_chicken.jpg",
        "imageType": "jpg",
        "rating": 4.5,
        "price": 28.8,
        "description": "经典川菜，鸡肉嫩滑，花生酥脆，麻辣鲜香",
        "category": "川菜",
        "reviewCount": 128,
        "isAvailable": true
      },
      {
        "id": "2b3c4d5e6f7g",
        "dishName": "红烧肉",
        "restaurant": "百景园食堂",
        "imageData": "/imgs/hongshao_pork.jpg",
        "imageType": "jpg",
        "rating": 4.8,
        "price": 35.0,
        "description": "肥而不腻，入口即化的经典红烧肉",
        "category": "本帮菜",
        "reviewCount": 256,
        "isAvailable": true
      },
      {
        "id": "3c4d5e6f7g8h",
        "dishName": "麻婆豆腐",
        "restaurant": "东园食堂",
        "imageData": "/imgs/mapo_tofu.jpg",
        "imageType": "jpg",
        "rating": 4.2,
        "price": 18.0,
        "description": "麻辣鲜香，豆腐嫩滑，经典川菜素食",
        "category": "川菜",
        "reviewCount": 89,
        "isAvailable": true
      },
      {
        "id": "4d5e6f7g8h9i",
        "dishName": "鱼香肉丝",
        "restaurant": "西园食堂",
        "imageData": "/imgs/yuxiang_pork.jpg",
        "imageType": "jpg",
        "rating": 4.6,
        "price": 22.0,
        "description": "酸甜可口，色泽红润，下饭首选",
        "category": "川菜",
        "reviewCount": 167,
        "isAvailable": true
      },
      {
        "id": "5e6f7g8h9i0j",
        "dishName": "黄焖鸡米饭",
        "restaurant": "学子餐厅",
        "imageData": "/imgs/huangmen_chicken.jpg",
        "imageType": "jpg",
        "rating": 4.3,
        "price": 25.0,
        "description": "鸡肉鲜嫩，汤汁浓郁，米饭软糯",
        "category": "快餐",
        "reviewCount": 203,
        "isAvailable": true
      },
      {
        "id": "6f7g8h9i0j1k",
        "dishName": "猪肝粉",
        "restaurant": "东一食堂",
        "imageData": "/imgs/pork_liver_noodle.jpg",
        "imageType": "jpg",
        "rating": 4.3,
        "price": 8.0,
        "description": "新鲜猪肝搭配爽滑米粉，汤汁鲜美，营养丰富",
        "category": "主食",
        "reviewCount": 203,
        "isAvailable": true
      },
      {
        "id": "7g8h9i0j1k2l",
        "dishName": "回锅肉拌面",
        "restaurant": "东一食堂",
        "imageData": "/imgs/twice_cooked_pork_noodle.jpg",
        "imageType": "jpg",
        "rating": 3.0,
        "price": 11.0,
        "description": "香辣回锅肉与劲道面条完美结合，香气扑鼻",
        "category": "主食",
        "reviewCount": 203,
        "isAvailable": true
      },
      {
        "id": "8h9i0j1k2l3m",
        "dishName": "鸭脯轻食饭",
        "restaurant": "西一食堂",
        "imageData": "/imgs/duck_breast_healthy_rice.jpg",
        "imageType": "jpg",
        "rating": 4.3,
        "price": 14.0,
        "description": "低脂鸭脯肉搭配杂粮饭，健康轻食选择",
        "category": "主食",
        "reviewCount": 203,
        "isAvailable": true
      },
      {
        "id": "2a2b3c4d5e6f",
        "dishName": "宫保鸡丁",
        "restaurant": "百景园食堂",
        "imageData": "/imgs/gongbao_chicken.jpg",
        "imageType": "jpg",
        "rating": 4.5,
        "price": 28.8,
        "description": "经典川菜，鸡肉嫩滑，花生酥脆，麻辣鲜香",
        "category": "川菜",
        "reviewCount": 128,
        "isAvailable": true
      },
      {
        "id": "3b3c4d5e6f7g",
        "dishName": "红烧肉",
        "restaurant": "百景园食堂",
        "imageData": "/imgs/hongshao_pork.jpg",
        "imageType": "jpg",
        "rating": 4.8,
        "price": 35.0,
        "description": "肥而不腻，入口即化的经典红烧肉",
        "category": "本帮菜",
        "reviewCount": 256,
        "isAvailable": true
      },
      {
        "id": "4c4d5e6f7g8h",
        "dishName": "麻婆豆腐",
        "restaurant": "东园食堂",
        "imageData": "/imgs/mapo_tofu.jpg",
        "imageType": "jpg",
        "rating": 4.2,
        "price": 18.0,
        "description": "麻辣鲜香，豆腐嫩滑，经典川菜素食",
        "category": "川菜",
        "reviewCount": 89,
        "isAvailable": true
      },
      {
        "id": "5d5e6f7g8h9i",
        "dishName": "鱼香肉丝",
        "restaurant": "西园食堂",
        "imageData": "/imgs/yuxiang_pork.jpg",
        "imageType": "jpg",
        "rating": 4.6,
        "price": 22.0,
        "description": "酸甜可口，色泽红润，下饭首选",
        "category": "川菜",
        "reviewCount": 167,
        "isAvailable": true
      },
      {
        "id": "6e6f7g8h9i0j",
        "dishName": "黄焖鸡米饭",
        "restaurant": "学子餐厅",
        "imageData": "/imgs/huangmen_chicken.jpg",
        "imageType": "jpg",
        "rating": 4.3,
        "price": 25.0,
        "description": "鸡肉鲜嫩，汤汁浓郁，米饭软糯",
        "category": "快餐",
        "reviewCount": 203,
        "isAvailable": true
      },
      {
        "id": "7f7g8h9i0j1k",
        "dishName": "猪肝粉",
        "restaurant": "东一食堂",
        "imageData": "/imgs/pork_liver_noodle.jpg",
        "imageType": "jpg",
        "rating": 4.3,
        "price": 8.0,
        "description": "新鲜猪肝搭配爽滑米粉，汤汁鲜美，营养丰富",
        "category": "主食",
        "reviewCount": 203,
        "isAvailable": true
      },
      {
        "id": "8g8h9i0j1k2l",
        "dishName": "回锅肉拌面",
        "restaurant": "东一食堂",
        "imageData": "/imgs/twice_cooked_pork_noodle.jpg",
        "imageType": "jpg",
        "rating": 3.0,
        "price": 11.0,
        "description": "香辣回锅肉与劲道面条完美结合，香气扑鼻",
        "category": "主食",
        "reviewCount": 203,
        "isAvailable": true
      },
      {
        "id": "9h9i0j1k2l3m",
        "dishName": "鸭脯轻食饭",
        "restaurant": "西一食堂",
        "imageData": "/imgs/duck_breast_healthy_rice.jpg",
        "imageType": "jpg",
        "rating": 4.3,
        "price": 14.0,
        "description": "低脂鸭脯肉搭配杂粮饭，健康轻食选择",
        "category": "主食",
        "reviewCount": 203,
        "isAvailable": true
      }
    ]
  }
  